gitlabirced/__init__.py
gitlabirced/cli.py
gitlabirced/gitlabirced.py
gitlabirced/http_server.py
gitlabirced/irc_client.py
gitlabirced-0.5.0.dist-info/AUTHORS.rst
gitlabirced-0.5.0.dist-info/LICENSE
gitlabirced-0.5.0.dist-info/METADATA
gitlabirced-0.5.0.dist-info/WHEEL
gitlabirced-0.5.0.dist-info/entry_points.txt
gitlabirced-0.5.0.dist-info/top_level.txt
gitlabirced-0.5.0.dist-info/RECORD
