Metadata-Version: 2.1
Name: gitlabirced
Version: 0.5.0
Summary: IRC bot that connects with your GitLab projects
Home-page: https://gitlab.com/palvarez89/gitlabirced
Author: Pedro Alvarez Piedehierro
Author-email: pedro@alvarezpiedehierro.com
License: MIT license
Keywords: gitlabirced
Platform: UNKNOWN
Classifier: Development Status :: 4 - Beta
Classifier: Intended Audience :: Developers
Classifier: License :: OSI Approved :: MIT License
Classifier: Natural Language :: English
Classifier: Programming Language :: Python :: 3
Classifier: Programming Language :: Python :: 3.4
Classifier: Programming Language :: Python :: 3.5
Classifier: Programming Language :: Python :: 3.6
Classifier: Programming Language :: Python :: 3.7
Requires-Python: >=3
Requires-Dist: irc (==16.4)
Requires-Dist: click (==6.7)
Requires-Dist: requests (==2.21.0)
Requires-Dist: PyYAML (==5.1.1)
